MANIFEST.in
README.txt
setup.cfg
setup.py
yaco/__init__.py
yaco.deliverancethemeselector.egg-info/PKG-INFO
yaco.deliverancethemeselector.egg-info/SOURCES.txt
yaco.deliverancethemeselector.egg-info/dependency_links.txt
yaco.deliverancethemeselector.egg-info/entry_points.txt
yaco.deliverancethemeselector.egg-info/namespace_packages.txt
yaco.deliverancethemeselector.egg-info/not-zip-safe
yaco.deliverancethemeselector.egg-info/requires.txt
yaco.deliverancethemeselector.egg-info/top_level.txt
yaco/deliverancethemeselector/README.txt
yaco/deliverancethemeselector/__init__.py
yaco/deliverancethemeselector/config.py
yaco/deliverancethemeselector/configure.zcml
yaco/deliverancethemeselector/interfaces.py
yaco/deliverancethemeselector/profiles.zcml
yaco/deliverancethemeselector/tests.py
yaco/deliverancethemeselector/update_i18n.sh
yaco/deliverancethemeselector/version.txt
yaco/deliverancethemeselector/browser/__init__.py
yaco/deliverancethemeselector/browser/adapters.py
yaco/deliverancethemeselector/browser/configure.zcml
yaco/deliverancethemeselector/browser/content.py
yaco/deliverancethemeselector/browser/controlpanel.py
yaco/deliverancethemeselector/browser/traversal.py
yaco/deliverancethemeselector/browser/vocabularies.py
yaco/deliverancethemeselector/browser/images/icon.png
yaco/deliverancethemeselector/locales/yaco.deliverancethemeselector.pot
yaco/deliverancethemeselector/locales/en/LC_MESSAGES/yaco.deliverancethemeselector.po
yaco/deliverancethemeselector/locales/es/LC_MESSAGES/yaco.deliverancethemeselector.po
yaco/deliverancethemeselector/profiles/default/actions.xml
yaco/deliverancethemeselector/profiles/default/controlpanel.xml
yaco/deliverancethemeselector/profiles/default/metadata.xml
yaco/deliverancethemeselector/profiles/default/registry.xml
yaco/deliverancethemeselector/profiles/uninstall/controlpanel.xml
yaco/deliverancethemeselector/profiles/uninstall/metadata.xml
yaco/deliverancethemeselector/profiles/uninstall/registry.xml