Metadata-Version: 1.0
Name: yaco.deliverancethemeselector
Version: 1.0a1
Summary: Deliveranece theme selector
Home-page: https://svn.plone.org/svn/collective/yaco.deliverancethemeselector
Author: Juan A. Diaz [nueces]
Author-email: jdiaz@menttes.com
License: GPL
Platform: UNKNOWN
Classifier: Framework :: Plone
Classifier: Programming Language :: Python
Classifier: Topic :: Software Development :: Libraries :: Python Modules
